llm2slm/__init__.py
llm2slm/cli.py
llm2slm/py.typed
llm2slm/core/__init__.py
llm2slm/core/config.py
llm2slm/core/pipeline.py
llm2slm/providers/__init__.py
llm2slm/providers/anthropic.py
llm2slm/providers/base.py
llm2slm/providers/google.py
llm2slm/providers/liquid.py
llm2slm/providers/openai.py
llm2slm/server/__init__.py
llm2slm/server/app.py
llm2slm/slm/__init__.py
llm2slm/slm/benchmark.py
llm2slm/slm/export.py
llm2slm/slm/loaders.py
llm2slm/slm/metadata.py
llm2slm/slm/model.py
llm2slm/slm/runtime.py
llm2slm-0.1.0.dist-info/licenses/LICENSE.txt
llm2slm-0.1.0.dist-info/METADATA
llm2slm-0.1.0.dist-info/WHEEL
llm2slm-0.1.0.dist-info/entry_points.txt
llm2slm-0.1.0.dist-info/top_level.txt
llm2slm-0.1.0.dist-info/RECORD
