Metadata-Version: 2.4
Name: llm2slm
Version: 0.1.0
Summary: Convert Large Language Models to Small Language Models with CLI, Web UI, and IDE integration
Author-email: Kolerr Lab <ricky@kolerr.com>
Maintainer-email: Kolerr Lab <lab.kolerr@kolerr.com>
License: MIT
Project-URL: Homepage, https://github.com/Kolerr-Lab/llm2slm-oss
Project-URL: Documentation, https://llm2slm-oss.readthedocs.io
Project-URL: Repository, https://github.com/Kolerr-Lab/llm2slm-oss
Project-URL: Issues, https://github.com/Kolerr-Lab/llm2slm-oss/issues
Project-URL: Changelog, https://github.com/Kolerr-Lab/llm2slm-oss/blob/main/CHANGELOG.md
Keywords: machine-learning,llm,slm,model-compression,ai,nlp,quantization,distillation
Classifier: Development Status :: 3 - Alpha
Classifier: Intended Audience :: Developers
Classifier: Intended Audience :: Science/Research
Classifier: License :: OSI Approved :: MIT License
Classifier: Operating System :: OS Independent
Classifier: Programming Language :: Python :: 3
Classifier: Programming Language :: Python :: 3.8
Classifier: Programming Language :: Python :: 3.9
Classifier: Programming Language :: Python :: 3.10
Classifier: Programming Language :: Python :: 3.11
Classifier: Programming Language :: Python :: 3.12
Classifier: Topic :: Scientific/Engineering :: Artificial Intelligence
Classifier: Topic :: Software Development :: Libraries :: Python Modules
Requires-Python: >=3.8
License-File: LICENSE.txt
Requires-Dist: click>=8.0.0
Requires-Dist: fastapi>=0.104.0
Requires-Dist: httpx>=0.25.0
Requires-Dist: numpy>=1.21.0
Requires-Dist: pydantic>=2.0.0
Requires-Dist: PyYAML>=6.0
Requires-Dist: tqdm>=4.64.0
Requires-Dist: uvicorn[standard]>=0.24.0
Provides-Extra: dev
Requires-Dist: pytest>=7.0.0; extra == "dev"
Requires-Dist: pytest-asyncio>=0.21.0; extra == "dev"
Requires-Dist: pytest-cov>=4.0.0; extra == "dev"
Requires-Dist: pytest-mock>=3.10.0; extra == "dev"
Requires-Dist: black>=23.0.0; extra == "dev"
Requires-Dist: isort>=5.12.0; extra == "dev"
Requires-Dist: ruff>=0.1.0; extra == "dev"
Requires-Dist: mypy>=1.5.0; extra == "dev"
Requires-Dist: pre-commit>=3.0.0; extra == "dev"
Provides-Extra: server
Requires-Dist: uvicorn[standard]>=0.24.0; extra == "server"
Requires-Dist: gunicorn>=21.0.0; extra == "server"
Provides-Extra: onnx
Requires-Dist: onnx>=1.14.0; extra == "onnx"
Requires-Dist: onnxruntime>=1.16.0; extra == "onnx"
Provides-Extra: tensorrt
Requires-Dist: tensorrt>=8.6.0; extra == "tensorrt"
Requires-Dist: pycuda>=2022.2; extra == "tensorrt"
Provides-Extra: all
Requires-Dist: llm2slm[dev,onnx,server,tensorrt]; extra == "all"
Dynamic: license-file
